Metadata-Version: 1.0
Name: jcproj-baiduscraper
Version: 0.0.6
Summary: this is a mess package to solve something
Home-page: UNKNOWN
Author: Li Jicher
Author-email: lijichen8c@163.com
License: UNKNOWN
Platform: UNKNOWN
